PYcmd/PYcmd.py
PYcmd/__init__.py
logrec/__init__.py
logrec/logrec.py
logrecandpycmd-4.8.4.dist-info/licenses/LICENSE
logrecandpycmd-4.8.4.dist-info/METADATA
logrecandpycmd-4.8.4.dist-info/WHEEL
logrecandpycmd-4.8.4.dist-info/top_level.txt
logrecandpycmd-4.8.4.dist-info/RECORD
