Metadata-Version: 2.4
Name: LogrecAndPYcmd
Version: 4.8.4
Summary: logrec: A quick record log's lib, Can search log file, And record(Or write) logs to a file. It's easy, Please use "logging" library. I know, My lib is sucks, But I well publish it to github. PYcmd: This program is a command prompt tool for managing files.
Author-email: Git32-Design <git32mail@qq.com>
License-Expression: MIT AND (Apache-2.0 OR BSD-3-Clause)
Project-URL: Homepage, https://github.com/Git32-Design/logrec-and-PYcmd
Project-URL: Documentation, https://readthedocs.org
Project-URL: Repository, https://github.com/Git32-Design/logrec-and-PYcmd
Project-URL: Issues, https://github.com/Git32-Design/logrec-and-PYcmd/issues
Project-URL: Changelog, https://github.com/Git32-Design/logrec-and-PYcmd/blob/main/Update%20msgs.md
Project-URL: MyHomepage, https://github.com/Git32-Design
Project-URL: DOWNLOAD, https://github.com/Git32-Design/logrec-and-PYcmd/releases
Project-URL: PYPI, https://pypi.org/project/LogrecAndPYcmd/
Keywords: log,logger,recording,search,management,file,logging,debug,custom cmd
Classifier: Development Status :: 5 - Production/Stable
Classifier: Intended Audience :: Developers
Classifier: Intended Audience :: System Administrators
Classifier: Operating System :: OS Independent
Classifier: Programming Language :: Python :: 3
Classifier: Programming Language :: Python :: 3.8
Classifier: Programming Language :: Python :: 3.9
Classifier: Programming Language :: Python :: 3.10
Classifier: Programming Language :: Python :: 3.11
Classifier: Programming Language :: Python :: 3.12
Classifier: Programming Language :: Python :: 3.13
Classifier: Topic :: Software Development :: Libraries :: Python Modules
Classifier: Topic :: System :: Logging
Classifier: Topic :: System :: Systems Administration
Classifier: Topic :: Utilities
Requires-Python: >=3.8
License-File: LICENSE
Provides-Extra: test
Requires-Dist: pytest>=7.0; extra == "test"
Dynamic: license-file
